coben/__init__.py
coben/coben.py
coben/utils/component_utils.py
coben/utils/directory_utils.py
coben/utils/doc_utils.py
coben/utils/file_utils.py
coben/utils/git_utils.py
coben/utils/parse_c.py
coben/utils/parse_zephyr.py
coben/utils/private_function_to_c.py
coben/utils/project_setup.py
coben/utils/puml_utils.py
coben/utils/search_toolchain.py
coben/utils/template_factory.py
coben/utils/utils.py
coben/utils/templates/CMakeLists.txt.j2
coben/utils/templates/Component.cpp.j2
coben/utils/templates/Component.hpp.j2
coben/utils/templates/Component.md.j2
coben/utils/templates/Component.puml.j2
coben/utils/templates/Project_CMakeLists.txt.j2
coben/utils/templates/crosscompile.txt.j2
coben/utils/templates/gitignore.j2
coben/utils/templates/index.md.j2
coben/utils/templates/ipo.cpp.j2
coben/utils/templates/ipo.hpp.j2
coben/utils/templates/main.cpp.j2
coben/utils/templates/mkdocs.yml.j2
coben/utils/templates/project.puml.j2
coben/utils/templates/serializer.hpp.j2
coben-0.1.1.dist-info/LICENSE
coben-0.1.1.dist-info/METADATA
coben-0.1.1.dist-info/WHEEL
coben-0.1.1.dist-info/entry_points.txt
coben-0.1.1.dist-info/top_level.txt
coben-0.1.1.dist-info/RECORD
